{"cameraMode":{"drawMode":0,"name":"Shaded","section":"Shading Mode"},"sceneLighting":false,"audioPlay":false,"sceneViewState":{"m_AlwaysRefresh":false,"showFog":true,"showSkybox":false,"showFlares":true,"showImageEffects":true,"showParticleSystems":true,"showVisualEffectGraphs":true,"m_FxEnabled":true},"in2DMode":false,"pivot":{"x":-0.18315547704696656,"y":0.7072173357009888,"z":0.0778040885925293},"rotation":{"x":-0.0476888045668602,"y":-0.9445329904556274,"z":0.28587090969085696,"w":-0.15537531673908235},"size":1.5286672115325928,"orthographic":false}